GhostGate/__init__.py
GhostGate-1.0.0.dist-info/METADATA
GhostGate-1.0.0.dist-info/WHEEL
GhostGate-1.0.0.dist-info/top_level.txt
GhostGate-1.0.0.dist-info/RECORD
