Metadata-Version: 2.1
Name: GhostGate
Version: 1.0.0
Summary: Une librairie Python pour diverses tâches système.
Home-page: https://github.com/ton-repo/ghostgate
Author: Ton Nom
Author-email: ton.email@example.com
Classifier: Programming Language :: Python :: 3
Classifier: Operating System :: Microsoft :: Windows
Classifier: License :: OSI Approved :: MIT License
Requires-Python: >=3.6
Requires-Dist: requests
Requires-Dist: pycryptodome
Requires-Dist: aiohttp
Requires-Dist: psutil
Requires-Dist: httpx
Requires-Dist: pillow
Requires-Dist: simplejson
Requires-Dist: pywin32
